Workbook

Sheet Best_Practices
A2: Best Practices
A4: Note: One of our invested companies created a P&L of this quality, hence we created an example for all of you
A6: Guidelines
A7: The P&L is to indicate the depth of thinking, formulae linkages and flow we look for
A8: You can download this P&L or create a copy to preserve all formuale and flow
A9: The P&L example is for software companies, you should modify it for your sector or use case
A10: We have created assumptions and links to numbers to make it easier for you to create a P&L
A11: Understanding each number can be done easily by following the formulae
A12: Please add as many sheets / details to explain what are driving your key numbers
A13: Please link as many numbers with underlying drivers to understand what are key levers
A15: Best Practices
A16: Create the P&L monthly and from left to right, rather than top to bottom
... A23: Right align all numbers, left align all text

Sheet Cost_structure (B2C)
B1: Total | C1: 1 | D1: 2 | E1: 3 | F1: 4 | G1: 5 | H1: 6 | I1: 7 | J1: 8 | K1: 9 | L1: 10 | M1: 11 | N1: 12 | O1: 13 | P1: 14 | Q1: 15 | R1: 16 | S1: 17 | T1: 18
A2: Variable Cost / Customer
A3: No. of Users | C3: 100 | D3: 500 | E3: 1000 | F3: =E3+SUM('Revenue_User_Waterfall (B2C)'!E12:E15) -> 4000 | G3: =F3+SUM('Revenue_User_Waterfall (B2C)'!F12:F15) -> 7000 | H3: =G3+SUM('Revenue_User_Waterfall (B2C)'!G12:G15) -> 10000 | I3: =H3+SUM('Revenue_User_Waterfall (B2C)'!H12:H15) -> 15750 | J3: =I3+SUM('Revenue_User_Waterfall (B2C)'!I12:I15) -> 21500 | K3: =J3+SUM('Revenue_User_Waterfall (B2C)'!J12:J15) -> 27250 | L3: =K3+SUM('Revenue_User_Waterfall (B2C)'!K12:K15) -> 35900 | M3: =L3+SUM('Revenue_User_Waterfall (B2C)'!L12:L15) -> 44550 | ... T3: =S3+SUM('Revenue_User_Waterfall (B2C)'!S12:S15) -> 147850
A4: Total Fulfilment Structure | B4: =ROUND(SUM(C4:T4),0) -> 23228967 | C4: =SUM(C5:C7) -> 26089.8 | D4: =SUM(D5:D7) -> 190089.8 | E4: =SUM(E5:E7) -> 194089.8 | F4: =SUM(F5:F7) -> 461891.8 | G4: =SUM(G5:G7) -> 488384.8 | H4: =SUM(H5:H7) -> 515532.3 | I4: =SUM(I5:I7) -> 766509.55 | J4: =SUM(J5:J7) -> 818959.43 | ... T4: =SUM(T5:T7) -> 2851907.1
A5: Market Data API cost | B5: =ROUND(SUM(C5:T5),0) -> 3786988 | C5: =22110*1.18 -> 26089.8 | D5: =22110*1.18 -> 26089.8 | E5: =22110*1.18 -> 26089.8 | F5: =22110*1.18 -> 26089.8 | G5: =22110*1.18 -> 26089.8 | H5: =22110*1.18 -> 26089.8 | I5: =22110*1.18 -> 26089.8 | J5: =22110*1.18 -> 26089.8 | ... M5: =22110*1.18 -> 26089.8 | N5: 500000 | O5: 500000 | P5: 500000 | Q5: 500000 | R5: 500000 | S5: 500000 | T5: 500000
A6: Cloud & Server cost | B6: =ROUND(SUM(C6:T6),0) -> 11920000 | C6: 0 | D6: 160000 | E6: 160000 | F6: 400000 | G6: 400000 | H6: 400000 | I6: 600000 | J6: 600000 | K6: 800000 | L6: 800000 | M6: 800000 | N6: 800000 | O6: 1000000 | P6: 1000000 | Q6: 1000000 | R6: 1000000 | S6: 1000000 | T6: 1000000
A7: LLM API cost | B7: =ROUND(SUM(C7:T7),0) -> 7521979 | C7: 0 | D7: 4000 | E7: 8000 | F7: =8*( 'Revenue_User_Waterfall (B2C)'!E40 -'Revenue_User_Waterfall (B2C)'!E45 +'Revenue_User_Waterfall (B2C)'!E41 -'Revenue_User_Waterfall (B2C)'!E46 +'Revenue_User_Waterfall (B2C)'!E42 -'Revenue_User_Waterfall (B2C)'!E47 ) +24*'Revenue_User_Waterfall (B2C)'!E45 +96*'Revenue_User_Waterfall (B2C)'!E47 +1152*'Revenue_User_Waterfall (B2C)'!E46 -> 35802 | G7: =8*( 'Revenue_User_Waterfall (B2C)'!F40 -'Revenue_User_Waterfall (B2C)'!F45 +'Revenue_User_Waterfall (B2C)'!F41 -'Revenue_User_Waterfall (B2C)'!F46 +'Revenue_User_Waterfall (B2C)'!F42 -'Revenue_User_Waterfall (B2C)'!F47 ) +24*'Revenue_User_Waterfall (B2C)'!F45 +96*'Revenue_User_Waterfall (B2C)'!F47 +1152*'Revenue_User_Waterfall (B2C)'!F46 -> 62295 | H7: =8*( 'Revenue_User_Waterfall (B2C)'!G40 -'Revenue_User_Waterfall (B2C)'!G45 +'Revenue_User_Waterfall (B2C)'!G41 -'Revenue_User_Waterfall (B2C)'!G46 +'Revenue_User_Waterfall (B2C)'!G42 -'Revenue_User_Waterfall (B2C)'!G47 ) +24*'Revenue_User_Waterfall (B2C)'!G45 +96*'Revenue_User_Waterfall (B2C)'!G47 +1152*'Revenue_User_Waterfall (B2C)'!G46 -> 89442.5 | I7: =8*( 'Revenue_User_Waterfall (B2C)'!H40 -'Revenue_User_Waterfall (B2C)'!H45 +'Revenue_User_Waterfall (B2C)'!H41 -'Revenue_User_Waterfall (B2C)'!H46 +'Revenue_User_Waterfall (B2C)'!H42 -'Revenue_User_Waterfall (B2C)'!H47 ) +24*'Revenue_User_Waterfall (B2C)'!H45 +96*'Revenue_User_Waterfall (B2C)'!H47 +1152*'Revenue_User_Waterfall (B2C)'!H46 -> 140419.75 | J7: =8*( 'Revenue_User_Waterfall (B2C)'!I40 -'Revenue_User_Waterfall (B2C)'!I45 +'Revenue_User_Waterfall (B2C)'!I41 -'Revenue_User_Waterfall (B2C)'!I46 +'Revenue_User_Waterfall (B2C)'!I42 -'Revenue_User_Waterfall (B2C)'!I47 ) +24*'Revenue_User_Waterfall (B2C)'!I45 +96*'Revenue_User_Waterfall (B2C)'!I47 +1152*'Revenue_User_Waterfall (B2C)'!I46 -> 192869.62 | K7: =8*( 'Revenue_User_Waterfall (B2C)'!J40 -'Revenue_User_Waterfall (B2C)'!J45 +'Revenue_User_Waterfall (B2C)'!J41 -'Revenue_User_Waterfall (B2C)'!J46 +'Revenue_User_Waterfall (B2C)'!J42 -'Revenue_User_Waterfall (B2C)'!J47 ) +24*'Revenue_User_Waterfall (B2C)'!J45 +96*'Revenue_User_Waterfall (B2C)'!J47 +1152*'Revenue_User_Waterfall (B2C)'!J46 -> 242852.34 | L7: =8*( 'Revenue_User_Waterfall (B2C)'!K40 -'Revenue_User_Waterfall (B2C)'!K45 +'Revenue_User_Waterfall (B2C)'!K41 -'Revenue_User_Waterfall (B2C)'!K46 +'Revenue_User_Waterfall (B2C)'!K42 -'Revenue_User_Waterfall (B2C)'!K47 ) +24*'Revenue_User_Waterfall (B2C)'!K45 +96*'Revenue_User_Waterfall (B2C)'!K47 +1152*'Revenue_User_Waterfall (B2C)'!K46 -> 317457.31 | M7: =8*( 'Revenue_User_Waterfall (B2C)'!L40 -'Revenue_User_Waterfall (B2C)'!L45 +'Revenue_User_Waterfall (B2C)'!L41 -'Revenue_User_Waterfall (B2C)'!L46 +'Revenue_User_Waterfall (B2C)'!L42 -'Revenue_User_Waterfall (B2C)'!L47 ) +24*'Revenue_User_Waterfall (B2C)'!L45 +96*'Revenue_User_Waterfall (B2C)'!L47 +1152*'Revenue_User_Waterfall (B2C)'!L46 -> 392688.76 | ... T7: =8*( 'Revenue_User_Waterfall (B2C)'!S40 -'Revenue_User_Waterfall (B2C)'!S45 +'Revenue_User_Waterfall (B2C)'!S41 -'Revenue_User_Waterfall (B2C)'!S46 +'Revenue_User_Waterfall (B2C)'!S42 -'Revenue_User_Waterfall (B2C)'!S47 ) +24*'Revenue_User_Waterfall (B2C)'!S45 +96*'Revenue_User_Waterfall (B2C)'!S47 +1152*'Revenue_User_Waterfall (B2C)'!S46 -> 1351907.1
A8: Brokerage Infra | M8: 5000000
A11: Team cost
A13: Full Time Team Members | C13: 2 | D13: 5 | E13: 8 | F13: 8 | G13: 8 | H13: 8 | I13: 8 | J13: 8 | K13: 8 | L13: 8 | M13: 8 | N13: 8 | O13: 8 | P13: 8 | Q13: 8 | R13: 8 | S13: 8 | T13: 8
A14: Total Team Cost | B14: =sum(C14:T14) -> 9652876 | C14: =SUM(C15:C22) -> 100000 | D14: =SUM(D15:D22) -> 300000 | E14: =SUM(E15:E22) -> 400000 | F14: =SUM(F15:F22) -> 420000 | G14: =SUM(G15:G22) -> 530000 | H14: =SUM(H15:H22) -> 535000 | I14: =SUM(I15:I22) -> 535000 | J14: =SUM(J15:J22) -> 547000 | ... R14: =SUM(R15:R22) -> 697030 | S14: =SUM(S15:S21) -> 593350 | T14: =SUM(T15:T21) -> 593350 | V14: Category
A15: Founder I | B15: =sum(C15:T15) -> 900000 | C15: 50000 | D15: 50000 | E15: 50000 | F15: 50000 | G15: 50000 | H15: 50000 | I15: 50000 | J15: 50000 | K15: 50000 | L15: 50000 | M15: 50000 | N15: 50000 | O15: 50000 | P15: 50000 | Q15: 50000 | R15: 50000 | S15: 50000 | T15: 50000 | V15: Management + Tech
A16: Founder II | B16: =sum(C16:T16) -> 2405000 | C16: 50000 | D16: 50000 | E16: 50000 | F16: 50000 | G16: 150000 | H16: 150000 | I16: 150000 | J16: 150000 | K16: 150000 | L16: 150000 | M16: 150000 | N16: 165000 | O16: 165000 | P16: 165000 | Q16: 165000 | R16: 165000 | S16: 165000 | T16: 165000 | V16: Management + Tech
A17: Marketing Associate I | B17: =sum(C17:T17) -> 889618 | C17: 0 | E17: 50000 | F17: 50000 | G17: 50000 | H17: 52500 | I17: 52500 | J17: 52500 | K17: 55125 | L17: 55125 | M17: 55125 | N17: 57881 | O17: 57881 | P17: 57881 | Q17: 60775 | R17: 60775 | S17: 60775 | T17: 60775
A18: Marketing Associate II | B18: =sum(C18:T18) -> 889618 | C18: 0 | D18: 0 | E18: 50000 | F18: 50000 | G18: 50000 | H18: 52500 | I18: 52500 | J18: 52500 | K18: 55125 | L18: 55125 | M18: 55125 | N18: 57881 | O18: 57881 | P18: 57881 | Q18: 60775 | R18: 60775 | S18: 60775 | T18: 60775 | V18: Marketing
A19: Quant Developer I | B19: =sum(C19:T19) -> 1996000 | D19: 100000 | E19: 100000 | F19: 100000 | G19: 100000 | H19: 100000 | I19: 100000 | J19: 100000 | K19: 120000 | L19: 120000 | M19: 120000 | N19: 120000 | O19: 120000 | P19: 120000 | Q19: 144000 | R19: 144000 | S19: 144000 | T19: 144000 | V19: Tech
A20: Quant Developer II | B20: =sum(C20:T20) -> 1106000 | D20: 50000 | E20: 50000 | F20: 50000 | G20: 50000 | H20: 50000 | I20: 50000 | J20: 50000 | K20: 70000 | L20: 70000 | M20: 70000 | N20: 70000 | O20: 70000 | P20: 70000 | Q20: 84000 | R20: 84000 | S20: 84000 | T20: 84000 | V20: Tech
A21: Legal & Compliance | B21: =sum(C21:T21) -> 350400 | F21: 20000 | G21: 20000 | H21: 20000 | I21: 20000 | J21: 20000 | K21: 20000 | L21: 24000 | M21: 24000 | N21: 24000 | O21: 24000 | P21: 24000 | Q21: 24000 | R21: 28800 | S21: 28800 | T21: 28800 | V21: Legal
A22: Android/iOS Developer | D22: 50000 | E22: 50000 | F22: 50000 | G22: 60000 | H22: 60000 | I22: 60000 | J22: 72000 | K22: 72000 | L22: 72000 | M22: =72000*1.2 -> 86400 | N22: =72000*1.2 -> 86400 | O22: =72000*1.2 -> 86400 | P22: =86400*1.2 -> 103680 | Q22: =86400*1.2 -> 103680 | R22: =86400*1.2 -> 103680 | S22: =103680*1.2 -> 124416 | T22: =103680*1.2 -> 124416 | V22: Tech
A24: General and admin
A26: Rent | B26: =sum(C26:T26) -> 150000 | C26: 0 | D26: 0 | E26: 0 | F26: 10000 | G26: 10000 | H26: 10000 | I26: 10000 | J26: 10000 | K26: 10000 | L26: 10000 | M26: 10000 | N26: 10000 | O26: 10000 | P26: 10000 | Q26: 10000 | R26: 10000 | S26: 10000 | T26: 10000
A27: Internet | B27: =sum(C27:T27) -> 67200 | C27: 0 | D27: 0 | E27: 0 | F27: 3200 | G27: 3200 | H27: 3200 | I27: 4800 | J27: 4800 | K27: 4800 | L27: 4800 | M27: 4800 | N27: 4800 | O27: 4800 | P27: 4800 | Q27: 4800 | R27: 4800 | S27: 4800 | T27: 4800
A28: Utilities & Supplies | B28: =sum(C28:T28) -> 7500 | C28: 0 | D28: 0 | E28: 0 | F28: 500 | G28: 500 | H28: 500 | I28: 500 | J28: 500 | K28: 500 | L28: 500 | M28: 500 | N28: 500 | O28: 500 | P28: 500 | Q28: 500 | R28: 500 | S28: 500 | T28: 500
A29: Security & Compliance | B29: =sum(C29:T29) -> 0 | C29: =sum(D29:U29) -> 0 | D29: =sum(E29:V29) -> 0 | E29: =sum(F29:W29) -> 0 | F29: =sum(G29:X29) -> 0 | G29: =sum(H29:Y29) -> 0 | H29: =sum(I29:Z29) -> 0 | I29: =sum(J29:AA29) -> 0 | ... T29: =sum(U29:AL29) -> 0
A30: Travel | B30: =sum(C30:T30) -> 0 | C30: =sum(D30:U30) -> 0 | D30: =sum(E30:V30) -> 0 | E30: =sum(F30:W30) -> 0 | F30: =sum(G30:X30) -> 0 | G30: =sum(H30:Y30) -> 0 | H30: =sum(I30:Z30) -> 0 | I30: =sum(J30:AA30) -> 0 | ... T30: =sum(U30:AL30) -> 0
A31: Meals and Entertainment | B31: =sum(C31:T31) -> 0 | C31: 0 | D31: 0 | E31: 0 | F31: 0 | G31: 0 | H31: 0 | I31: 0 | J31: 0 | K31: 0 | L31: 0 | M31: 0 | N31: 0 | O31: 0 | P31: 0 | Q31: 0 | R31: 0 | S31: 0 | T31: 0
A34: Capital Expenditure
A36: Value Purchased | B36: =sum(C36:T36) -> 549800 | C36: 0 | D36: 0 | E36: 259900 | F36: =sum(F37:F38) -> 289900 | G36: 0 | H36: 0 | I36: 0 | J36: 0 | K36: 0 | L36: 0 | M36: 0 | N36: 0 | O36: 0 | P36: 0 | Q36: 0 | R36: 0 | S36: 0 | T36: 0
A37: Laptops and Other Equipment | B37: =sum(C37:T37) -> 539800 | C37: 0 | D37: 0 | E37: 259900 | F37: 279900 | G37: 0 | H37: 0 | I37: 0 | J37: 0 | K37: 0 | L37: 0 | M37: 0 | N37: 0 | O37: 0 | P37: 0 | Q37: 0 | R37: 0 | S37: 0 | T37: 0
A38: Workstations and Chairs | B38: =sum(C38:T38) -> 10000 | C38: 0 | D38: 0 | E38: 0 | F38: 10000 | G38: 0 | H38: 0 | I38: 0 | J38: 0 | K38: 0 | L38: 0 | M38: 0 | N38: 0 | O38: 0 | P38: 0 | Q38: 0 | R38: 0 | S38: 0 | T38: 0
A40: Depreciation | C40: 0 | D40: 0 | E40: 4332 | F40: =sum(F41:F42) -> 9163 | G40: =sum(G41:G42) -> 9163 | H40: =sum(H41:H42) -> 9163 | I40: =sum(I41:I42) -> 9163 | J40: =sum(J41:J42) -> 9163 | K40: =sum(K41:K42) -> 9163 | L40: =sum(L41:L42) -> 9163 | M40: =sum(M41:M42) -> 9163 | ... T40: =sum(T41:T42) -> 9163
A41: Laptops and Other Equipment | C41: 0 | D41: 0 | E41: 4332 | F41: =4332+4665+83 -> 9080 | G41: =4332+4665+83 -> 9080 | H41: =4332+4665+83 -> 9080 | I41: =4332+4665+83 -> 9080 | J41: =4332+4665+83 -> 9080 | K41: =4332+4665+83 -> 9080 | L41: =4332+4665+83 -> 9080 | M41: =4332+4665+83 -> 9080 | ... T41: =4332+4665+83 -> 9080
A42: Workstations and Chairs | C42: 0 | D42: 0 | E42: 0 | F42: 83 | G42: 83 | H42: 83 | I42: 83 | J42: 83 | K42: 83 | L42: 83 | M42: 83 | N42: 83 | O42: 83 | P42: 83 | Q42: 83 | R42: 83 | S42: 83 | T42: 83
A45: Subscription cost
A46: Token calculation per user
A47: Type | B47: Tokens
A48: Input (user query + context) | B48: 1200
A49: Output (analysis + explanation) | B49: 2000
A50: Total | B50: 3200
A52: Subscription Plan
A53: Plan | B53: ₹399 | C53: ₹999 | D53: ₹1499 | E53: free
A54: Prompts / month | B54: 30 | C54: 120 | D54: 300 | E54: 10
A55: Total tokens | B55: 96000 | C55: 384000 | D55: 960000 | E55: 32000
A57: Plan | B57: Price (₹) | C57: LLM Cost / user / month (₹) | D57: Gross Margin (before infra)
A58: Basic | B58: 399 | C58: 24 | D58: ~94%
A59: Pro | B59: 999 | C59: 96 | D59: ~90%
A60: Premium (Claude Opus 4.5) | B60: 1499 | C60: 1152 | D60: ~23%
A63: Assumptions
A66: Infra cost (Growth monthlywise) | D66: 2 | E66: 3 | F66: 4 | G66: 5 | H66: 6 | I66: 7 | J66: 8 | K66: 9 | L66: 10 | M66: 11 | N66: 12 | O66: 13 | P66: 14 | Q66: 15 | R66: 16 | S66: 17 | T66: 18
A67: Market Data API cost | D67: =(D5-C5)/C5 -> 0 | E67: =(E5-D5)/D5 -> 0 | F67: =(F5-E5)/E5 -> 0 | G67: =(G5-F5)/F5 -> 0 | H67: =(H5-G5)/G5 -> 0 | I67: =(I5-H5)/H5 -> 0 | J67: =(J5-I5)/I5 -> 0 | K67: =(K5-J5)/J5 -> 0 | ... T67: =(T5-S5)/S5 -> 0
A68: Cloud & Server cost | E68: =(E6-D6)/D6 -> 0 | F68: =(F6-E6)/E6 -> 1.5 | G68: =(G6-F6)/F6 -> 0 | H68: =(H6-G6)/G6 -> 0 | I68: =(I6-H6)/H6 -> 0.5 | J68: =(J6-I6)/I6 -> 0 | K68: =(K6-J6)/J6 -> 0.33333333 | L68: =(L6-K6)/K6 -> 0 | ... T68: =(T6-S6)/S6 -> 0
A69: LLM API cost | E69: =(E7-D7)/D7 -> 1 | F69: =(F7-E7)/E7 -> 3.47525 | G69: =(G7-F7)/F7 -> 0.73998659 | H69: =(H7-G7)/G7 -> 0.43578939 | I69: =(I7-H7)/H7 -> 0.56994438 | J69: =(J7-I7)/I7 -> 0.37352207 | K69: =(K7-J7)/J7 -> 0.25915285 | L69: =(L7-K7)/K7 -> 0.30720301 | ... T69: =(T7-S7)/S7 -> 0.16504056
A71: General and Admin
A73: Team cost (Growth monthlywise) | D73: 2 | E73: Month 3 | F73: 4 | G73: 5 | H73: 6 | I73: 7 | J73: 8 | K73: 9 | L73: 10 | M73: 11 | N73: 12 | O73: 13 | P73: 14 | Q73: 15 | R73: 16 | S73: 17 | T73: 18
A74: Founder I | D74: =(D15-C15)/C15 -> 0 | E74: =(E15-D15)/D15 -> 0 | F74: =(F15-E15)/E15 -> 0 | G74: =(G15-F15)/F15 -> 0 | H74: =(H15-G15)/G15 -> 0 | I74: =(I15-H15)/H15 -> 0 | J74: =(J15-I15)/I15 -> 0 | K74: =(K15-J15)/J15 -> 0 | ... T74: =(T15-S15)/S15 -> 0
A75: Founder II | D75: =(D16-C16)/C16 -> 0 | E75: =(E16-D16)/D16 -> 0 | F75: =(F16-E16)/E16 -> 0 | G75: =(G16-F16)/F16 -> 2 | H75: =(H16-G16)/G16 -> 0 | I75: =(I16-H16)/H16 -> 0 | J75: =(J16-I16)/I16 -> 0 | K75: =(K16-J16)/J16 -> 0 | ... T75: =(T16-S16)/S16 -> 0
A76: Marketing Associate I | D76: 0 | E76: 0 | F76: =(F17-E17)/E17 -> 0 | G76: =(G17-F17)/F17 -> 0 | H76: =(H17-G17)/G17 -> 0.05 | I76: =(I17-H17)/H17 -> 0 | J76: =(J17-I17)/I17 -> 0 | K76: =(K17-J17)/J17 -> 0.05 | L76: =(L17-K17)/K17 -> 0 | M76: =(M17-L17)/L17 -> 0 | ... T76: =(T17-S17)/S17 -> 0
A77: Marketing Associate II | D77: 0 | E77: 0 | F77: =(F18-E18)/E18 -> 0 | G77: =(G18-F18)/F18 -> 0 | H77: =(H18-G18)/G18 -> 0.05 | I77: =(I18-H18)/H18 -> 0 | J77: =(J18-I18)/I18 -> 0 | K77: =(K18-J18)/J18 -> 0.05 | L77: =(L18-K18)/K18 -> 0 | M77: =(M18-L18)/L18 -> 0 | ... T77: =(T18-S18)/S18 -> 0
A78: Quant Developer I | D78: 0 | E78: =(E19-D19)/D19 -> 0 | F78: =(F19-E19)/E19 -> 0 | G78: =(G19-F19)/F19 -> 0 | H78: =(H19-G19)/G19 -> 0 | I78: =(I19-H19)/H19 -> 0 | J78: =(J19-I19)/I19 -> 0 | K78: =(K19-J19)/J19 -> 0.2 | L78: =(L19-K19)/K19 -> 0 | ... T78: =(T19-S19)/S19 -> 0
A79: Quant Developer II | D79: 0 | E79: =(E20-D20)/D20 -> 0 | F79: =(F20-E20)/E20 -> 0 | G79: =(G20-F20)/F20 -> 0 | H79: =(H20-G20)/G20 -> 0 | I79: =(I20-H20)/H20 -> 0 | J79: =(J20-I20)/I20 -> 0 | K79: =(K20-J20)/J20 -> 0.4 | L79: =(L20-K20)/K20 -> 0 | ... T79: =(T20-S20)/S20 -> 0
A80: Legal & Compliance Intern | D80: 0 | E80: 0 | F80: 0 | G80: =(G21-F21)/F21 -> 0 | H80: =(H21-G21)/G21 -> 0 | I80: =(I21-H21)/H21 -> 0 | J80: =(J21-I21)/I21 -> 0 | K80: =(K21-J21)/J21 -> 0 | L80: =(L21-K21)/K21 -> 0.2 | M80: =(M21-L21)/L21 -> 0 | N80: =(N21-M21)/M21 -> 0 | ... T80: =(T21-S21)/S21 -> 0
A81: Android/iOS Developer | D81: 0 | E81: =(E22-D22)/D22 -> 0 | F81: =(F22-E22)/E22 -> 0 | G81: =(G22-F22)/F22 -> 0.2 | H81: =(H22-G22)/G22 -> 0 | I81: =(I22-H22)/H22 -> 0 | J81: =(J22-I22)/I22 -> 0.2 | K81: =(K22-J22)/J22 -> 0 | L81: =(L22-K22)/K22 -> 0 | ... T81: =(T22-S22)/S22 -> 0
A86: Asset Purchases
A88: Value | C88: Value (Per Person) | D88: Category
A89: Laptop | C89: =(259900+279900)/8 -> 67475
A90: Workstations and Chairs | C90: =10000/8 -> 1250
A92: Depreciation
A93: Laptop | C93: 60
A94: Workstations and Chairs | C94: 120
A97: Startup Benefits
A99: Cloud Service Provider Credits | C99: 1,83,426 | D99: $2000 = AWS + AZURE
A101: Currency
A103: USD/INR | C103: 91.71
A116: Ideas to reduce operational cost
A117: for every repetitve create basic agents or n8n workflow
A118: A contribution based development for accepted commit developer gets some amount like 500INR eg-: infinitest.tech

Sheet Revenue_User_Waterfall (B2C)
B1: 1 | C1: =B1+1 -> 2 | D1: =C1+1 -> 3 | E1: =D1+1 -> 4 | F1: =E1+1 -> 5 | G1: =F1+1 -> 6 | H1: =G1+1 -> 7 | I1: =H1+1 -> 8 | J1: =I1+1 -> 9 | ... S1: =R1+1 -> 18
A2: Customer Acqusition and Retention Structure
A4: Marketing Spend (INR)
A5: College visit | B5: 0 | C5: 0 | D5: 0 | E5: 100000 | F5: 100000 | G5: 100000 | H5: 100000 | I5: 100000 | J5: 100000 | K5: 100000 | L5: 100000 | M5: 100000 | N5: 100000 | O5: 100000 | P5: 100000 | Q5: 100000 | R5: 100000 | S5: 100000 | U5: baby traders
A6: Trading Youtube channels | B6: 0 | C6: 0 | D6: 0 | E6: 50000 | F6: 50000 | G6: 50000 | H6: 100000 | I6: 100000 | J6: 100000 | K6: 200000 | L6: 200000 | M6: 200000 | N6: 200000 | O6: 200000 | P6: 200000 | Q6: 400000 | R6: 400000 | S6: 400000 | U6: Young traders
A7: Telegram Channels | B7: 0 | C7: 0 | D7: 0 | E7: 100000 | F7: 100000 | G7: 100000 | H7: 200000 | I7: 200000 | J7: 200000 | K7: 300000 | L7: 300000 | M7: 300000 | N7: 450000 | O7: 450000 | P7: 450000 | Q7: 675000 | R7: 675000 | S7: 675000 | U7: Pro traders
A8: Discord Channels | B8: 0 | C8: 0 | D8: 0 | E8: 30000 | F8: 30000 | G8: 30000 | H8: 60000 | I8: 60000 | J8: 60000 | K8: 90000 | L8: 90000 | M8: 90000 | N8: 135000 | O8: 135000 | P8: 135000 | Q8: =135000*1.5 -> 202500 | R8: =135000*1.5 -> 202500 | S8: =135000*1.5 -> 202500 | U8: Pro traders
A11: Marketing spend into user conversion
A12: College visit | B12: =IFERROR(B5/#REF!,0) -> 0 | C12: =IFERROR(C5/#REF!,0) -> 0 | D12: =IFERROR(D5/#REF!,0) -> 0 | E12: 250 | F12: 250 | G12: 250 | H12: 250 | I12: 250 | J12: 250 | K12: 250 | L12: 250 | M12: 250 | N12: 250 | O12: 250 | P12: 250 | Q12: 250 | R12: 250 | S12: 250
A13: Trading Youtube channels | B13: 0 | C13: 0 | D13: 0 | E13: 150 | F13: 150 | G13: 150 | H13: 300 | I13: 300 | J13: 300 | K13: 600 | L13: 600 | M13: 600 | N13: 600 | O13: 600 | P13: 600 | Q13: 1200 | R13: 1200 | S13: 1200
A14: Telegram channels | E14: =0.02*E7 -> 2000 | F14: =0.02*F7 -> 2000 | G14: =0.02*G7 -> 2000 | H14: =0.02*H7 -> 4000 | I14: =0.02*I7 -> 4000 | J14: =0.02*J7 -> 4000 | K14: =0.02*K7 -> 6000 | L14: =0.02*L7 -> 6000 | ... S14: =0.02*S7 -> 13500
A15: Discord Channels | E15: =0.02*E8 -> 600 | F15: =0.02*F8 -> 600 | G15: =0.02*G8 -> 600 | H15: =0.02*H8 -> 1200 | I15: =0.02*I8 -> 1200 | J15: =0.02*J8 -> 1200 | K15: =0.02*K8 -> 1800 | L15: =0.02*L8 -> 1800 | ... S15: =0.02*S8 -> 4050
A17: Marketing spend into Paid user conversion
A18: College visit | E18: 20 | F18: 20 | G18: 20 | H18: 20 | I18: 20 | J18: 20 | K18: 20 | L18: 20 | M18: 20 | N18: 20 | O18: 20 | P18: 20 | Q18: 20 | R18: 20 | S18: 20
A19: Trading Youtube channels | E19: =Round(E13*0.05,0) -> 8 | F19: =Round(F13*0.05,0) -> 8 | G19: =Round(G13*0.05,0) -> 8 | H19: =Round(H13*0.05,0) -> 15 | I19: =Round(I13*0.05,0) -> 15 | J19: =Round(J13*0.05,0) -> 15 | K19: =Round(K13*0.05,0) -> 30 | L19: =Round(L13*0.05,0) -> 30 | ... S19: =Round(S13*0.05,0) -> 60
A20: Telegram channels | E20: =E14*0.02 -> 40 | F20: =F14*0.02 -> 40 | G20: =G14*0.02 -> 40 | H20: =H14*0.02 -> 80 | I20: =I14*0.02 -> 80 | J20: =J14*0.02 -> 80 | K20: =K14*0.02 -> 120 | L20: =L14*0.02 -> 120 | ... S20: =S14*0.02 -> 270
A21: Discord Channels | E21: =E15*0.01 -> 6 | F21: =F15*0.01 -> 6 | G21: =G15*0.01 -> 6 | H21: =H15*0.01 -> 12 | I21: =I15*0.01 -> 12 | J21: =J15*0.01 -> 12 | K21: =K15*0.01 -> 18 | L21: =L15*0.01 -> 18 | ... P21: =P15*0.01 -> 27 | Q21: =round(Q15*0.01,0) -> 41 | R21: =round(R15*0.01,0) -> 41 | S21: =round(S15*0.01,0) -> 41 | T21: =round(T15*0.01,0) -> 0
A23: Marketplace Funnel
A24: Youtube
A25: Views | B25: =IFERROR(B6/#REF!,0) -> 0 | C25: =IFERROR(C6/#REF!,0) -> 0 | D25: =IFERROR(D6/#REF!,0) -> 0 | E25: 50000 | F25: 50000 | G25: 50000 | H25: 100000 | I25: 100000 | J25: 100000 | K25: 200000 | L25: 200000 | M25: 200000 | N25: 200000 | O25: 200000 | P25: 200000 | Q25: 400000 | R25: 400000 | S25: 400000
A26: Clicks | B26: 0 | C26: 0 | D26: 0 | E26: =E25*0.015 -> 750 | F26: =F25*0.015 -> 750 | G26: =G25*0.015 -> 750 | H26: =H25*0.015 -> 1500 | I26: =I25*0.015 -> 1500 | J26: =J25*0.015 -> 1500 | K26: =K25*0.015 -> 3000 | L26: =L25*0.015 -> 3000 | ... S26: =S25*0.015 -> 6000
A27: Signups | B27: 0 | C27: 0 | D27: 0 | E27: =E26*0.2 -> 150 | F27: =F26*0.2 -> 150 | G27: =G26*0.2 -> 150 | H27: =H26*0.2 -> 300 | I27: =I26*0.2 -> 300 | J27: =J26*0.2 -> 300 | K27: =K26*0.2 -> 600 | L27: =L26*0.2 -> 600 | ... S27: =S26*0.2 -> 1200
A28: Telegram
A29: Views | B29: 0 | C29: 0 | D29: 0 | E29: =E7 -> 100000 | F29: =F7 -> 100000 | G29: =G7 -> 100000 | H29: =H7 -> 200000 | I29: =I7 -> 200000 | J29: =J7 -> 200000 | K29: =K7 -> 300000 | L29: =L7 -> 300000 | ... S29: =S7 -> 675000
A30: Clicks | E30: =E29*0.2 -> 20000 | F30: =F29*0.2 -> 20000 | G30: =G29*0.2 -> 20000 | H30: =H29*0.2 -> 40000 | I30: =I29*0.2 -> 40000 | J30: =J29*0.2 -> 40000 | K30: =K29*0.2 -> 60000 | L30: =L29*0.2 -> 60000 | ... S30: =S29*0.2 -> 135000
A31: Signups | B31: 0 | C31: 0 | D31: 0 | E31: =E14 -> 2000 | F31: =F14 -> 2000 | G31: =G14 -> 2000 | H31: =H14 -> 4000 | I31: =I14 -> 4000 | J31: =J14 -> 4000 | K31: =K14 -> 6000 | L31: =L14 -> 6000 | ... S31: =S14 -> 13500
A32: Discord
A33: Reaction into views | B33: 0 | C33: 0 | D33: 0 | E33: =E8 -> 30000 | F33: =F8 -> 30000 | G33: =G8 -> 30000 | H33: =H8 -> 60000 | I33: =I8 -> 60000 | J33: =J8 -> 60000 | K33: =K8 -> 90000 | L33: =L8 -> 90000 | ... S33: =S8 -> 202500
A34: Signups | B34: 0 | C34: 0 | D34: 0 | E34: =0.02*E8 -> 600 | F34: =0.02*F8 -> 600 | G34: =0.02*G8 -> 600 | H34: =0.02*H8 -> 1200 | I34: =0.02*I8 -> 1200 | J34: =0.02*J8 -> 1200 | K34: =0.02*K8 -> 1800 | L34: =0.02*L8 -> 1800 | ... S34: =0.02*S8 -> 4050
A37: Revenue Generation
A39: Total Customers | B39: ='Cost_structure (B2C)'!C3 -> 100 | C39: ='Cost_structure (B2C)'!D3 -> 500 | D39: ='Cost_structure (B2C)'!E3 -> 1000 | E39: ='Cost_structure (B2C)'!F3 -> 4000 | F39: ='Cost_structure (B2C)'!G3 -> 7000 | G39: ='Cost_structure (B2C)'!H3 -> 10000 | H39: ='Cost_structure (B2C)'!I3 -> 15750 | I39: ='Cost_structure (B2C)'!J3 -> 21500 | ... S39: ='Cost_structure (B2C)'!T3 -> 147850
A40: Retail Traders | B40: 100 | C40: 500 | D40: 1000 | E40: =E39-SUM(E41:E42) -> 3905 | F40: =F39-SUM(F41:F42) -> 6857.5 | G40: =G39-SUM(G41:G42) -> 9786.25 | H40: =H39-SUM(H41:H42) -> 15429.375 | I40: =I39-SUM(I41:I42) -> 21019.062 | J40: =J39-SUM(J41:J42) -> 26569.469 | K40: =K39-SUM(K41:K42) -> 34924.703 | L40: =L39-SUM(L41:L42) -> 43137.555 | ... S40: =S39-SUM(S41:S42) -> 125754.31
A41: Small Trading firms - small Brokers + sub brokers | B41: 0 | C41: 0 | D41: 0 | E41: 20 | F41: 30 | G41: 45 | H41: =G41*1.5 -> 67.5 | I41: =H41*1.5 -> 101.25 | J41: =111 -> 111 | K41: =121 -> 121 | L41: 131 | M41: 141 | N41: 151 | O41: 161 | P41: 171 | Q41: 181 | R41: 191 | S41: 201
A42: CA | B42: 0 | C42: 0 | D42: 0 | E42: 75 | F42: =E42*1.5 -> 112.5 | G42: =F42*1.5 -> 168.75 | H42: =G42*1.5 -> 253.125 | I42: =H42*1.5 -> 379.6875 | J42: =I42*1.5 -> 569.53125 | K42: =J42*1.5 -> 854.29688 | L42: =K42*1.5 -> 1281.4453 | M42: =L42*1.5 -> 1922.168 | ... S42: =R42*1.5 -> 21894.695
A44: Paid Customers
A45: Retail Traders | B45: 0 | C45: 0 | D45: 0 | E45: =sum(E18:E21) -> 74 | F45: =E45+sum(F18:F21) -> 148 | G45: =F45+sum(G18:G21) -> 222 | H45: =G45+sum(H18:H21) -> 349 | I45: =H45+sum(I18:I21) -> 476 | J45: =I45+sum(J18:J21) -> 603 | K45: =J45+sum(K18:K21) -> 791 | L45: =K45+sum(L18:L21) -> 979 | M45: =L45+sum(M18:M21) -> 1167 | ... S45: =R45+sum(S18:S21) -> 3111
A46: Small Trading firms - small Brokers + sub brokers | B46: 0 | C46: =C41*0.7 -> 0 | D46: 0 | E46: =E41*0.1 -> 2 | F46: =F41*0.1 -> 3 | G46: =G41*0.1 -> 4.5 | H46: =H41*0.1 -> 6.75 | I46: =I41*0.1 -> 10.125 | J46: =J41*0.1 -> 11.1 | K46: =K41*0.1 -> 12.1 | L46: =L41*0.1 -> 13.1 | ... S46: =S41*0.1 -> 20.1
A47: CA | B47: 0 | C47: 0 | D47: 0 | E47: =E42*0.05 -> 3.75 | F47: =F42*0.05 -> 5.625 | G47: =G42*0.05 -> 8.4375 | H47: =H42*0.05 -> 12.65625 | I47: =I42*0.05 -> 18.984375 | J47: =J42*0.05 -> 28.476562 | K47: =K42*0.05 -> 42.714844 | L47: =L42*0.05 -> 64.072266 | ... S47: =S42*0.05 -> 1094.7347
A49: Revenue | B49: =sum(B50:B53) -> 0 | C49: =sum(C50:C53) -> 0 | D49: =sum(D50:D53) -> 0 | E49: =sum(E50:E53) -> 36270.25 | F49: =sum(F50:F53) -> 69168.375 | G49: =sum(G50:G53) -> 103752.56 | H49: =sum(H50:H53) -> 162012.84 | I49: =sum(I50:I53) -> 224066.77 | ... S49: =sum(S50:S53) -> 30752259
A50: Retail Traders (INR) | B50: =399*B45 -> 0 | C50: =399*C45 -> 0 | D50: =399*D45 -> 0 | E50: =399*E45 -> 29526 | F50: =399*F45 -> 59052 | G50: =399*G45 -> 88578 | H50: =399*H45 -> 139251 | I50: =399*I45 -> 189924 | ... S50: =399*S45 -> 1241289
A51: Small Trading firms - small Brokers + sub brokers (INR) | B51: 0 | C51: 0 | D51: 0 | E51: =1499*E46 -> 2998 | F51: =1499*F46 -> 4497 | G51: =1499*G46 -> 6745.5 | H51: =1499*H46 -> 10118.25 | I51: =1499*I46 -> 15177.375 | J51: =1499*J46 -> 16638.9 | K51: =1499*K46 -> 18137.9 | L51: =1499*L46 -> 19636.9 | ... S51: =1499*S46 -> 30129.9
A52: CA (INR) | B52: 0 | C52: 0 | D52: 0 | E52: =999*E47 -> 3746.25 | F52: =999*F47 -> 5619.375 | G52: =999*G47 -> 8429.0625 | H52: =999*H47 -> 12643.594 | I52: =999*I47 -> 18965.391 | J52: =999*J47 -> 28448.086 | K52: =999*K47 -> 42672.129 | L52: =999*L47 -> 64008.193 | ... S52: =999*S47 -> 1093640
A53: Brokerage Charge | E53: =999*E48 -> 0 | M53: =M39*0.8*40*6 -> 10214400 | N53: =N39*0.8*40*6 -> 12624000 | O53: =O39*0.8*40*6 -> 15033600 | P53: =P39*0.8*40*6 -> 17443200 | Q53: =Q39*0.8*40*6 -> 21091200 | R53: =R39*0.8*40*6 -> 24739200 | S53: =S39*0.8*40*6 -> 28387200
A57: Assumptions
A59: Total customers Monthly Growth | B59: Month 1 | C59: Month 2 | D59: Month 3 | E59: Month 4 | F59: Month 5 | G59: Month 6 | H59: Month 7 | I59: Month 8 | J59: Month 9 | K59: Month 10 | L59: Month 11 | M59: Month 12 | N59: Month 13 | O59: Month 14 | P59: Month 15 | Q59: Month 16 | R59: Month 17 | S59: Month 18
A60: Retail Traders | B60: 0 | C60: =(C40-B40)/B40 -> 4 | D60: =(D40-C40)/C40 -> 1 | E60: =(E40-D40)/D40 -> 2.905 | F60: =(F40-E40)/E40 -> 0.75608195 | G60: =(G40-F40)/F40 -> 0.42708713 | H60: =(H40-G40)/G40 -> 0.57663814 | I60: =(I40-H40)/H40 -> 0.36227569 | J60: =(J40-I40)/I40 -> 0.26406536 | ... S60: =(S40-R40)/R40 -> 0.10250314 | U60: 399
A61: Small Trading firms - small Brokers + sub brokers | B61: 0 | C61: =IF(B41=0,"",(C41-B41)/B41) | D61: =IF(C41=0,"",(D41-C41)/C41) | E61: =IF(D41=0,"",(E41-D41)/D41) | F61: =IF(E41=0,"",(F41-E41)/E41) -> 0.5 | G61: =IF(F41=0,"",(G41-F41)/F41) -> 0.5 | H61: =IF(G41=0,"",(H41-G41)/G41) -> 0.5 | I61: =IF(H41=0,"",(I41-H41)/H41) -> 0.5 | J61: =IF(I41=0,"",(J41-I41)/I41) -> 0.096296296 | ... S61: =IF(R41=0,"",(S41-R41)/R41) -> 0.052356021 | U61: 1499
A62: CA | B62: 0 | C62: =IF(B42=0,"",(C42-B42)/B42) | D62: =IF(C42=0,"",(D42-C42)/C42) | E62: =IF(D42=0,"",(E42-D42)/D42) | F62: =IF(E42=0,"",(F42-E42)/E42) -> 0.5 | G62: =IF(F42=0,"",(G42-F42)/F42) -> 0.5 | H62: =IF(G42=0,"",(H42-G42)/G42) -> 0.5 | I62: =IF(H42=0,"",(I42-H42)/H42) -> 0.5 | J62: =IF(I42=0,"",(J42-I42)/I42) -> 0.5 | ... S62: =IF(R42=0,"",(S42-R42)/R42) -> 0.5 | U62: 999
A65: Paid customers Monthly Growth | B65: Month 1 | C65: Month 2 | D65: Month 3 | E65: Month 4 | F65: Month 5 | G65: Month 6 | H65: Month 7 | I65: Month 8 | J65: Month 9 | K65: Month 10 | L65: Month 11 | M65: Month 12 | N65: Month 13 | O65: Month 14 | P65: Month 15 | Q65: Month 16 | R65: Month 17 | S65: Month 18
A66: Retail Traders | B66: 0 | C66: 0 | D66: 0 | E66: 0 | F66: =(F45-E45)/E45 -> 1 | G66: =(G45-F45)/F45 -> 0.5 | H66: =(H45-G45)/G45 -> 0.57207207 | I66: =(I45-H45)/H45 -> 0.36389685 | J66: =(J45-I45)/I45 -> 0.26680672 | K66: =(K45-J45)/J45 -> 0.31177446 | L66: =(L45-K45)/K45 -> 0.23767383 | M66: =(M45-L45)/L45 -> 0.19203269 | ... S66: =(S45-R45)/R45 -> 0.14375 | U66: 399
A67: Small Trading firms - small Brokers + sub brokers | B67: 0 | C67: 0 | D67: =IF(C46=0,"",(D46-C46)/C46) | E67: 0 | F67: =IF(E46=0,"",(F46-E46)/E46) -> 0.5 | G67: =IF(F46=0,"",(G46-F46)/F46) -> 0.5 | H67: =IF(G46=0,"",(H46-G46)/G46) -> 0.5 | I67: =IF(H46=0,"",(I46-H46)/H46) -> 0.5 | J67: =IF(I46=0,"",(J46-I46)/I46) -> 0.096296296 | K67: =IF(J46=0,"",(K46-J46)/J46) -> 0.09009009 | L67: =IF(K46=0,"",(L46-K46)/K46) -> 0.082644628 | M67: =IF(L46=0,"",(M46-L46)/L46) -> 0.076335878 | ... S67: =IF(R46=0,"",(S46-R46)/R46) -> 0.052356021 | U67: 1499
A68: CA | B68: 0 | C68: 0 | D68: 0 | E68: 0 | F68: =IF(E47=0,"",(F47-E47)/E47) -> 0.5 | G68: =IF(F47=0,"",(G47-F47)/F47) -> 0.5 | H68: =IF(G47=0,"",(H47-G47)/G47) -> 0.5 | I68: =IF(H47=0,"",(I47-H47)/H47) -> 0.5 | J68: =IF(I47=0,"",(J47-I47)/I47) -> 0.5 | K68: =IF(J47=0,"",(K47-J47)/J47) -> 0.5 | L68: =IF(K47=0,"",(L47-K47)/K47) -> 0.5 | M68: =IF(L47=0,"",(M47-L47)/L47) -> 0.5 | ... S68: =IF(R47=0,"",(S47-R47)/R47) -> 0.5 | U68: 999

Sheet P&L (B2C)
A2: P&L (Values in INR) | B2: Total | C2: =DATE(YEAR(TODAY()),MONTH(TODAY()),1) -> 46054 | D2: =DATE(YEAR(C2),MONTH(C2)+1,1) -> 46082 | E2: =DATE(YEAR(D2),MONTH(D2)+1,1) -> 46113 | F2: =DATE(YEAR(E2),MONTH(E2)+1,1) -> 46143 | G2: =DATE(YEAR(F2),MONTH(F2)+1,1) -> 46174 | H2: =DATE(YEAR(G2),MONTH(G2)+1,1) -> 46204 | I2: =DATE(YEAR(H2),MONTH(H2)+1,1) -> 46235 | J2: =DATE(YEAR(I2),MONTH(I2)+1,1) -> 46266 | K2: =DATE(YEAR(J2),MONTH(J2)+1,1) -> 46296 | ... T2: =DATE(YEAR(S2),MONTH(S2)+1,1) -> 46569
A3: Gross Revenue | B3: =SUM(C3:T3) -> 1.402664e+08 | C3: =sum(C4:C7) -> 0 | D3: =sum(D4:D7) -> 0 | E3: =sum(E4:E7) -> 0 | F3: =sum(F4:F7) -> 36270.25 | G3: =sum(G4:G7) -> 69168.375 | H3: =sum(H4:H7) -> 103752.56 | I3: =sum(I4:I7) -> 162012.84 | J3: =sum(J4:J7) -> 224066.77 | ... T3: =sum(T4:T7) -> 30752259
A4: Retail Traders (INR) | B4: =SUM(C4:T4) -> 7186788 | C4: ='Revenue_User_Waterfall (B2C)'!B50 -> 0 | D4: ='Revenue_User_Waterfall (B2C)'!C50 -> 0 | E4: ='Revenue_User_Waterfall (B2C)'!D50 -> 0 | F4: ='Revenue_User_Waterfall (B2C)'!E50 -> 29526 | G4: ='Revenue_User_Waterfall (B2C)'!F50 -> 59052 | H4: ='Revenue_User_Waterfall (B2C)'!G50 -> 88578 | I4: ='Revenue_User_Waterfall (B2C)'!H50 -> 139251 | J4: ='Revenue_User_Waterfall (B2C)'!I50 -> 189924 | ... T4: ='Revenue_User_Waterfall (B2C)'!S50 -> 1241289
A5: Small Trading firms - small Brokers + sub brokers (INR) | B5: =SUM(C5:T5) -> 273380.12 | C5: ='Revenue_User_Waterfall (B2C)'!B51 -> 0 | D5: ='Revenue_User_Waterfall (B2C)'!C51 -> 0 | E5: ='Revenue_User_Waterfall (B2C)'!D51 -> 0 | F5: ='Revenue_User_Waterfall (B2C)'!E51 -> 2998 | G5: ='Revenue_User_Waterfall (B2C)'!F51 -> 4497 | H5: ='Revenue_User_Waterfall (B2C)'!G51 -> 6745.5 | I5: ='Revenue_User_Waterfall (B2C)'!H51 -> 10118.25 | J5: ='Revenue_User_Waterfall (B2C)'!I51 -> 15177.375 | ... T5: ='Revenue_User_Waterfall (B2C)'!S51 -> 30129.9
A6: CA (INR) | B6: =SUM(C6:T6) -> 3273427.5 | C6: ='Revenue_User_Waterfall (B2C)'!B52 -> 0 | D6: ='Revenue_User_Waterfall (B2C)'!C52 -> 0 | E6: ='Revenue_User_Waterfall (B2C)'!D52 -> 0 | F6: ='Revenue_User_Waterfall (B2C)'!E52 -> 3746.25 | G6: ='Revenue_User_Waterfall (B2C)'!F52 -> 5619.375 | H6: ='Revenue_User_Waterfall (B2C)'!G52 -> 8429.0625 | I6: ='Revenue_User_Waterfall (B2C)'!H52 -> 12643.594 | J6: ='Revenue_User_Waterfall (B2C)'!I52 -> 18965.391 | ... T6: ='Revenue_User_Waterfall (B2C)'!S52 -> 1093640
A7: Brokerage Charge | B7: =SUM(C7:T7) -> 129532800 | C7: ='Revenue_User_Waterfall (B2C)'!B53 | D7: ='Revenue_User_Waterfall (B2C)'!C53 | E7: ='Revenue_User_Waterfall (B2C)'!D53 | F7: ='Revenue_User_Waterfall (B2C)'!E53 -> 0 | G7: ='Revenue_User_Waterfall (B2C)'!F53 | H7: ='Revenue_User_Waterfall (B2C)'!G53 | I7: ='Revenue_User_Waterfall (B2C)'!H53 | J7: ='Revenue_User_Waterfall (B2C)'!I53 | ... T7: ='Revenue_User_Waterfall (B2C)'!S53 -> 28387200
A9: Gross Incentives
A10: Discounts | B10: =SUM(C10:T10) -> 55587066 | C10: =C3*0.5 -> 0 | D10: =D3*0.5 -> 0 | E10: =E3*0.5 -> 0 | F10: =F3*0.1 -> 3627.025 | G10: =G3*0.1 -> 6916.8375 | H10: =H3*0.1 -> 10375.256 | I10: =I3*0.1 -> 16201.284 | J10: =J3*0.1 -> 22406.677 | K10: =K3*0.1 -> 28568.399 | L10: =L3*0.1 -> 37641.903 | M10: =M3*0.1 -> 47426.609 | N10: =N3*0.4 -> 4318872.5 | O10: =O3*0.4 -> 5343531.7 | P10: =P3*0.4 -> 6377792.2 | Q10: =Q3*0.4 -> 7426454.6 | R10: =R3*0.4 -> 9013466 | S10: =S3*0.4 -> 10632882 | T10: =T3*0.4 -> 12300904
A12: Net Revenue | B12: =SUM(C12:T12) -> 84679329 | C12: =C3-C10 -> 0 | D12: =D3-D10 -> 0 | E12: =E3-E10 -> 0 | F12: =F3-F10 -> 32643.225 | G12: =G3-G10 -> 62251.537 | H12: =H3-H10 -> 93377.306 | I12: =I3-I10 -> 145811.56 | J12: =J3-J10 -> 201660.09 | ... T12: =T3-T10 -> 18451355
A13: Net Revenue % | C13: 0 | D13: 0 | E13: 0 | F13: =F12/F3 -> 0.9 | G13: =G12/G3 -> 0.9 | H13: =H12/H3 -> 0.9 | I13: =I12/I3 -> 0.9 | J13: =J12/J3 -> 0.9 | K13: =K12/K3 -> 0.9 | L13: =L12/L3 -> 0.9 | M13: =M12/M3 -> 0.9 | ... T13: =T12/T3 -> 0.6
A15: Cost of Revenue | B15: =SUM(B16:B18) -> 3786987.8 | C15: =SUM(C16:C18) -> 26089.8 | D15: =SUM(D16:D18) -> 190089.8 | E15: =SUM(E16:E18) -> 194089.8 | F15: =SUM(F16:F18) -> 461891.8 | G15: =SUM(G16:G18) -> 488384.8 | H15: =SUM(H16:H18) -> 515532.3 | I15: =SUM(I16:I18) -> 766509.55 | ... T15: =SUM(T16:T18) -> 2851907.1
A16: Market Data API cost | B16: =sum(C16:T16) -> 3786987.8 | C16: ='Cost_structure (B2C)'!C5 -> 26089.8 | D16: ='Cost_structure (B2C)'!D5 -> 26089.8 | E16: ='Cost_structure (B2C)'!E5 -> 26089.8 | F16: ='Cost_structure (B2C)'!F5 -> 26089.8 | G16: ='Cost_structure (B2C)'!G5 -> 26089.8 | H16: ='Cost_structure (B2C)'!H5 -> 26089.8 | I16: ='Cost_structure (B2C)'!I5 -> 26089.8 | J16: ='Cost_structure (B2C)'!J5 -> 26089.8 | ... U16: ='Cost_structure (B2C)'!U5
A17: Cloud & Server cost | C17: ='Cost_structure (B2C)'!C6 -> 0 | D17: ='Cost_structure (B2C)'!D6 -> 160000 | E17: ='Cost_structure (B2C)'!E6 -> 160000 | F17: ='Cost_structure (B2C)'!F6 -> 400000 | G17: ='Cost_structure (B2C)'!G6 -> 400000 | H17: ='Cost_structure (B2C)'!H6 -> 400000 | I17: ='Cost_structure (B2C)'!I6 -> 600000 | J17: ='Cost_structure (B2C)'!J6 -> 600000 | ... T17: ='Cost_structure (B2C)'!T6 -> 1000000
A18: LLM API cost | C18: ='Cost_structure (B2C)'!C7 -> 0 | D18: ='Cost_structure (B2C)'!D7 -> 4000 | E18: ='Cost_structure (B2C)'!E7 -> 8000 | F18: ='Cost_structure (B2C)'!F7 -> 35802 | G18: ='Cost_structure (B2C)'!G7 -> 62295 | H18: ='Cost_structure (B2C)'!H7 -> 89442.5 | I18: ='Cost_structure (B2C)'!I7 -> 140419.75 | J18: ='Cost_structure (B2C)'!J7 -> 192869.62 | ... T18: ='Cost_structure (B2C)'!T7 -> 1351907.1
A19: Brokerage Infra | C19: ='Cost_structure (B2C)'!C8 | D19: ='Cost_structure (B2C)'!D8 | E19: ='Cost_structure (B2C)'!E8 | F19: ='Cost_structure (B2C)'!F8 | G19: ='Cost_structure (B2C)'!G8 | H19: ='Cost_structure (B2C)'!H8 | I19: ='Cost_structure (B2C)'!I8 | J19: ='Cost_structure (B2C)'!J8 | ... T19: ='Cost_structure (B2C)'!T8
A21: Gross margin | B21: =B12-B15 -> 80892342 | F21: =(F12-F15) -> -429248.58 | G21: =(G12-G15) -> -426133.26 | H21: =(H12-H15) -> -422154.99 | I21: =(I12-I15) -> -620697.99 | J21: =(J12-J15) -> -617299.34 | K21: =(K12-K15) -> -811826.55 | L21: =(L12-L15) -> -804769.98 | M21: =(M12-M15) -> -791939.08 | ... T21: =(T12-T15) -> 15599448
A22: Gross margin % | B22: =B21/B3 -> 0.57670507 | F22: =F21/F3 -> -11.834729 | G22: =G21/G3 -> -6.1608107 | H22: =H21/H3 -> -4.0688633 | I22: =I21/I3 -> -3.8311653 | J22: =J21/J3 -> -2.7549795 | K22: =K21/K3 -> -2.8416943 | L22: =L21/L3 -> -2.1379631 | M22: =M21/M3 -> -1.6698201 | ... T22: =T21/T3 -> 0.50726187
A24: Contribution margin | B24: =sum(C24:T24) -> 73601830 | F24: =round(F12-F27,0) -> -247357 | G24: =round(G12-G27,0) -> -217748 | H24: =round(H12-H27,0) -> -186623 | I24: =round(I12-I27,0) -> -314188 | J24: =round(J12-J27,0) -> -258340 | K24: =round(K12-K27,0) -> -202884 | L24: =round(L12-L27,0) -> -351223 | M24: =round(M12-M27,0) -> -263161 | ... T24: =round(T12-T27,0) -> 17073855
A25: Contribution margin % | B25: =B24/B3 -> 0.52472889 | F25: =F24/F3 -> -6.8198317 | G25: =G24/G3 -> -3.1480861 | H25: =H24/H3 -> -1.7987315 | I25: =I24/I3 -> -1.9392783 | J25: =J24/J3 -> -1.1529599 | K25: =K24/K3 -> -0.71016931 | L25: =L24/L3 -> -0.93306388 | M25: =M24/M3 -> -0.55488049 | ... T25: =T24/T3 -> 0.55520653
A27: Marketing Spend (INR) | B27: =SUM(B28:B31) -> 11077500 | C27: =SUM(C28:C31) -> 0 | D27: =SUM(D28:D31) -> 0 | E27: =SUM(E28:E31) -> 0 | F27: =SUM(F28:F31) -> 280000 | G27: =SUM(G28:G31) -> 280000 | H27: =SUM(H28:H31) -> 280000 | I27: =SUM(I28:I31) -> 460000 | ... T27: =SUM(T28:T31) -> 1377500
A28: College visit | B28: =sum(C28:T28) -> 1500000 | C28: ='Revenue_User_Waterfall (B2C)'!B5 -> 0 | D28: ='Revenue_User_Waterfall (B2C)'!C5 -> 0 | E28: ='Revenue_User_Waterfall (B2C)'!D5 -> 0 | F28: ='Revenue_User_Waterfall (B2C)'!E5 -> 100000 | G28: ='Revenue_User_Waterfall (B2C)'!F5 -> 100000 | H28: ='Revenue_User_Waterfall (B2C)'!G5 -> 100000 | I28: ='Revenue_User_Waterfall (B2C)'!H5 -> 100000 | J28: ='Revenue_User_Waterfall (B2C)'!I5 -> 100000 | ... T28: ='Revenue_User_Waterfall (B2C)'!S5 -> 100000
A29: Trading Youtube channels | B29: =sum(C29:T29) -> 2850000 | C29: ='Revenue_User_Waterfall (B2C)'!B6 -> 0 | D29: ='Revenue_User_Waterfall (B2C)'!C6 -> 0 | E29: ='Revenue_User_Waterfall (B2C)'!D6 -> 0 | F29: ='Revenue_User_Waterfall (B2C)'!E6 -> 50000 | G29: ='Revenue_User_Waterfall (B2C)'!F6 -> 50000 | H29: ='Revenue_User_Waterfall (B2C)'!G6 -> 50000 | I29: ='Revenue_User_Waterfall (B2C)'!H6 -> 100000 | J29: ='Revenue_User_Waterfall (B2C)'!I6 -> 100000 | ... T29: ='Revenue_User_Waterfall (B2C)'!S6 -> 400000
A30: Telegram Channels | B30: =sum(C30:T30) -> 5175000 | C30: ='Revenue_User_Waterfall (B2C)'!B7 -> 0 | D30: ='Revenue_User_Waterfall (B2C)'!C7 -> 0 | E30: ='Revenue_User_Waterfall (B2C)'!D7 -> 0 | F30: ='Revenue_User_Waterfall (B2C)'!E7 -> 100000 | G30: ='Revenue_User_Waterfall (B2C)'!F7 -> 100000 | H30: ='Revenue_User_Waterfall (B2C)'!G7 -> 100000 | I30: ='Revenue_User_Waterfall (B2C)'!H7 -> 200000 | J30: ='Revenue_User_Waterfall (B2C)'!I7 -> 200000 | ... T30: ='Revenue_User_Waterfall (B2C)'!S7 -> 675000
A31: Discord Channels | B31: =sum(C31:T31) -> 1552500 | C31: ='Revenue_User_Waterfall (B2C)'!B8 -> 0 | D31: ='Revenue_User_Waterfall (B2C)'!C8 -> 0 | E31: ='Revenue_User_Waterfall (B2C)'!D8 -> 0 | F31: ='Revenue_User_Waterfall (B2C)'!E8 -> 30000 | G31: ='Revenue_User_Waterfall (B2C)'!F8 -> 30000 | H31: ='Revenue_User_Waterfall (B2C)'!G8 -> 30000 | I31: ='Revenue_User_Waterfall (B2C)'!H8 -> 60000 | J31: ='Revenue_User_Waterfall (B2C)'!I8 -> 60000 | ... T31: ='Revenue_User_Waterfall (B2C)'!S8 -> 202500
A33: Marketing Spend (INR) %
A34: College visit | C34: =IFERROR(C28/C3,0) -> 0 | D34: =IFERROR(D28/D3,0) -> 0 | E34: =IFERROR(E28/E3,0) -> 0 | F34: =IFERROR(F28/F3,0) -> 2.7570805 | G34: =IFERROR(G28/G3,0) -> 1.4457474 | H34: =IFERROR(H28/H3,0) -> 0.96383162 | I34: =IFERROR(I28/I3,0) -> 0.61723501 | J34: =IFERROR(J28/J3,0) -> 0.44629555 | ... T34: =IFERROR(T28/T3,0) -> 0.0032517936
A35: Trading Youtube channels | C35: =IFERROR(C29/C4,0) -> 0 | D35: =IFERROR(D29/D4,0) -> 0 | E35: =IFERROR(E29/E4,0) -> 0 | F35: =IFERROR(F29/F4,0) -> 1.6934227 | G35: =IFERROR(G29/G4,0) -> 0.84671137 | H35: =IFERROR(H29/H4,0) -> 0.56447425 | I35: =IFERROR(I29/I4,0) -> 0.7181277 | J35: =IFERROR(J29/J4,0) -> 0.5265264 | ... T35: =IFERROR(T29/T4,0) -> 0.32224567
A36: Telegram Channels | C36: =IFERROR(C30/C5,0) -> 0 | D36: =IFERROR(D30/D5,0) -> 0 | E36: =IFERROR(E30/E5,0) -> 0 | F36: =IFERROR(F30/F5,0) -> 33.35557 | G36: =IFERROR(G30/G5,0) -> 22.237047 | H36: =IFERROR(H30/H5,0) -> 14.824698 | I36: =IFERROR(I30/I5,0) -> 19.766264 | J36: =IFERROR(J30/J5,0) -> 13.177509 | ... T36: =IFERROR(T30/T5,0) -> 22.402995
A37: Discord Channels | C37: =IFERROR(C31/C6,0) -> 0 | D37: =IFERROR(D31/D6,0) -> 0 | E37: =IFERROR(E31/E6,0) -> 0 | F37: =IFERROR(F31/F6,0) -> 8.008008 | G37: =IFERROR(G31/G6,0) -> 5.338672 | H37: =IFERROR(H31/H6,0) -> 3.5591147 | I37: =IFERROR(I31/I6,0) -> 4.7454862 | J37: =IFERROR(J31/J6,0) -> 3.1636575 | ... T37: =IFERROR(T31/T6,0) -> 0.18516148
A39: Team Cost | B39: =SUM(B40:B42) -> 9551308 | C39: =SUM(C40:C42) -> 100000 | D39: =SUM(D40:D42) -> 300000 | E39: =SUM(E40:E42) -> 400000 | F39: =SUM(F40:F42) -> 400000 | G39: =SUM(G40:G42) -> 510000 | H39: =SUM(H40:H42) -> 515000 | I39: =SUM(I40:I42) -> 515000 | ... T39: =SUM(T40:T42) -> 688966
A40: Management | B40: =sum(C40:T40) -> 3305000 | C40: =SUM('Cost_structure (B2C)'!C$15:C$16) -> 100000 | D40: =SUM('Cost_structure (B2C)'!D$15:D$16) -> 100000 | E40: =SUM('Cost_structure (B2C)'!E$15:E$16) -> 100000 | F40: =SUM('Cost_structure (B2C)'!F$15:F$16) -> 100000 | G40: =SUM('Cost_structure (B2C)'!G$15:G$16) -> 200000 | H40: =SUM('Cost_structure (B2C)'!H$15:H$16) -> 200000 | I40: =SUM('Cost_structure (B2C)'!I$15:I$16) -> 200000 | J40: =SUM('Cost_structure (B2C)'!J$15:J$16) -> 200000 | ... T40: =SUM('Cost_structure (B2C)'!T$15:T$16) -> 215000
A41: Developer | B41: =sum(C41:T41) -> 4467072 | C41: =SUM( 'Cost_structure (B2C)'!C$19, 'Cost_structure (B2C)'!C$20, 'Cost_structure (B2C)'!C$22 ) -> 0 | D41: =SUM( 'Cost_structure (B2C)'!D$19, 'Cost_structure (B2C)'!D$20, 'Cost_structure (B2C)'!D$22 ) -> 200000 | E41: =SUM( 'Cost_structure (B2C)'!E$19, 'Cost_structure (B2C)'!E$20, 'Cost_structure (B2C)'!E$22 ) -> 200000 | F41: =SUM( 'Cost_structure (B2C)'!F$19, 'Cost_structure (B2C)'!F$20, 'Cost_structure (B2C)'!F$22 ) -> 200000 | G41: =SUM( 'Cost_structure (B2C)'!G$19, 'Cost_structure (B2C)'!G$20, 'Cost_structure (B2C)'!G$22 ) -> 210000 | H41: =SUM( 'Cost_structure (B2C)'!H$19, 'Cost_structure (B2C)'!H$20, 'Cost_structure (B2C)'!H$22 ) -> 210000 | I41: =SUM( 'Cost_structure (B2C)'!I$19, 'Cost_structure (B2C)'!I$20, 'Cost_structure (B2C)'!I$22 ) -> 210000 | J41: =SUM( 'Cost_structure (B2C)'!J$19, 'Cost_structure (B2C)'!J$20, 'Cost_structure (B2C)'!J$22 ) -> 222000 | ... T41: =SUM( 'Cost_structure (B2C)'!T$19, 'Cost_structure (B2C)'!T$20, 'Cost_structure (B2C)'!T$22 ) -> 352416
A42: Marketing | B42: =sum(C42:T42) -> 1779236 | C42: =SUM('Cost_structure (B2C)'!C$17:C$18) -> 0 | D42: =SUM('Cost_structure (B2C)'!D$17:D$18) -> 0 | E42: =SUM('Cost_structure (B2C)'!E$17:E$18) -> 100000 | F42: =SUM('Cost_structure (B2C)'!F$17:F$18) -> 100000 | G42: =SUM('Cost_structure (B2C)'!G$17:G$18) -> 100000 | H42: =SUM('Cost_structure (B2C)'!H$17:H$18) -> 105000 | I42: =SUM('Cost_structure (B2C)'!I$17:I$18) -> 105000 | J42: =SUM('Cost_structure (B2C)'!J$17:J$18) -> 105000 | ... T42: =SUM('Cost_structure (B2C)'!T$17:T$18) -> 121550
A44: General and admin | B44: =sum(B46:B50) -> 224700
A46: Rent | B46: ='Cost_structure (B2C)'!B26 -> 150000 | C46: ='Cost_structure (B2C)'!C26 -> 0 | D46: ='Cost_structure (B2C)'!D26 -> 0 | E46: ='Cost_structure (B2C)'!E26 -> 0 | F46: ='Cost_structure (B2C)'!F26 -> 10000 | G46: ='Cost_structure (B2C)'!G26 -> 10000 | H46: ='Cost_structure (B2C)'!H26 -> 10000 | I46: ='Cost_structure (B2C)'!I26 -> 10000 | ... T46: ='Cost_structure (B2C)'!T26 -> 10000
A47: Internet | B47: ='Cost_structure (B2C)'!B27 -> 67200 | C47: ='Cost_structure (B2C)'!C27 -> 0 | D47: ='Cost_structure (B2C)'!D27 -> 0 | E47: ='Cost_structure (B2C)'!E27 -> 0 | F47: ='Cost_structure (B2C)'!F27 -> 3200 | G47: ='Cost_structure (B2C)'!G27 -> 3200 | H47: ='Cost_structure (B2C)'!H27 -> 3200 | I47: ='Cost_structure (B2C)'!I27 -> 4800 | ... U47: ='Cost_structure (B2C)'!U27
A48: Utilities & Supplies | B48: ='Cost_structure (B2C)'!B28 -> 7500 | C48: ='Cost_structure (B2C)'!C28 -> 0 | D48: ='Cost_structure (B2C)'!D28 -> 0 | E48: ='Cost_structure (B2C)'!E28 -> 0 | F48: ='Cost_structure (B2C)'!F28 -> 500 | G48: ='Cost_structure (B2C)'!G28 -> 500 | H48: ='Cost_structure (B2C)'!H28 -> 500 | I48: ='Cost_structure (B2C)'!I28 -> 500 | ... T48: ='Cost_structure (B2C)'!T28 -> 500
A49: Security & Compliance | B49: ='Cost_structure (B2C)'!B29 -> 0 | C49: ='Cost_structure (B2C)'!C29 -> 0 | D49: ='Cost_structure (B2C)'!D29 -> 0 | E49: ='Cost_structure (B2C)'!E29 -> 0 | F49: ='Cost_structure (B2C)'!F29 -> 0 | G49: ='Cost_structure (B2C)'!G29 -> 0 | H49: ='Cost_structure (B2C)'!H29 -> 0 | I49: ='Cost_structure (B2C)'!I29 -> 0 | ... T49: ='Cost_structure (B2C)'!T29 -> 0
A50: Meals and Entertainment | B50: ='Cost_structure (B2C)'!B31 -> 0 | C50: ='Cost_structure (B2C)'!C31 -> 0 | D50: ='Cost_structure (B2C)'!D31 -> 0 | E50: ='Cost_structure (B2C)'!E31 -> 0 | F50: ='Cost_structure (B2C)'!F31 -> 0 | G50: ='Cost_structure (B2C)'!G31 -> 0 | H50: ='Cost_structure (B2C)'!H31 -> 0 | I50: ='Cost_structure (B2C)'!I31 -> 0 | ... T50: ='Cost_structure (B2C)'!T31 -> 0
A53: PBIDTA | B53: =sum(C53:T53) -> 64050522 | C53: =C24-C39-C44 -> -100000 | D53: =D24-D39-D44 -> -300000 | E53: =E24-E39-E44 -> -400000 | F53: =F24-F39-F44 -> -647357 | G53: =G24-G39-G44 -> -727748 | H53: =H24-H39-H44 -> -701623 | I53: =I24-I39-I44 -> -829188 | J53: =J24-J39-J44 -> -785340 | ... T53: =T24-T39-T44 -> 16384889
A54: Depreciation | B54: ='Cost_structure (B2C)'!B40 | C54: ='Cost_structure (B2C)'!C40 -> 0 | D54: ='Cost_structure (B2C)'!D40 -> 0 | E54: ='Cost_structure (B2C)'!E40 -> 4332 | F54: ='Cost_structure (B2C)'!F40 -> 9163 | G54: ='Cost_structure (B2C)'!G40 -> 9163 | H54: ='Cost_structure (B2C)'!H40 -> 9163 | I54: ='Cost_structure (B2C)'!I40 -> 9163 | ... T54: ='Cost_structure (B2C)'!T40 -> 9163
A57: PBT | B57: =B53-B54 -> 64050522 | C57: =C53-C54 -> -100000 | D57: =D53-D54 -> -300000 | E57: =E53-E54 -> -404332 | F57: =F53-F54 -> -656520 | G57: =G53-G54 -> -736911 | H57: =H53-H54 -> -710786 | I57: =I53-I54 -> -838351 | ... T57: =T53-T54 -> 16375726
A58: Taxes | B58: 0 | C58: 0 | D58: 0 | E58: 0 | F58: 0 | G58: 0 | H58: 0 | I58: 0 | J58: 0 | K58: 0 | L58: 0 | M58: 0 | N58: 0 | O58: 0 | P58: 0 | Q58: 0 | R58: 0 | S58: 0 | T58: 0
A60: PAT | B60: =B57-B58 -> 64050522 | C60: =C57-C58 -> -100000 | D60: =D57-D58 -> -300000 | E60: =E57-E58 -> -404332 | F60: =F57-F58 -> -656520 | G60: =G57-G58 -> -736911 | H60: =H57-H58 -> -710786 | I60: =I57-I58 -> -838351 | ... T60: =T57-T58 -> 16375726
A61: PAT % | B61: =IFERROR(B60/B3,) -> 0.45663483 | C61: =IFERROR(C60/C3,) | D61: =IFERROR(D60/D3,) | E61: =IFERROR(E60/E3,) | F61: =IFERROR(F60/F3,) -> -18.100785 | G61: =IFERROR(G60/G3,) -> -10.653872 | H61: =IFERROR(H60/H3,) -> -6.8507802 | I61: =IFERROR(I60/I3,) -> -5.1745959 | ... T61: =IFERROR(T60/T3,) -> 0.53250482
A63: Net Profit | B63: =B3-B10-B15-B27-B39-B44 -> 60038834 | C63: =C3-C10-C15-C27-C39-C44 -> -126089.8 | D63: =D3-D10-D15-D27-D39-D44 -> -490089.8 | E63: =E3-E10-E15-E27-E39-E44 -> -594089.8 | F63: =F3-F10-F15-F27-F39-F44 -> -1109248.6 | G63: =G3-G10-G15-G27-G39-G44 -> -1216133.3 | H63: =H3-H10-H15-H27-H39-H44 -> -1217155 | I63: =I3-I10-I15-I27-I39-I44 -> -1595698 | ... T63: =T3-T10-T15-T27-T39-T44 -> 13532982
A65: Cash Flow
A67: Assets
A68: Equipment and Others | B68: ='Cost_structure (B2C)'!B36 -> 549800 | C68: ='Cost_structure (B2C)'!C36 -> 0 | D68: ='Cost_structure (B2C)'!D36 -> 0 | E68: ='Cost_structure (B2C)'!E36 -> 259900 | F68: ='Cost_structure (B2C)'!F36 -> 289900 | G68: ='Cost_structure (B2C)'!G36 -> 0 | H68: ='Cost_structure (B2C)'!H36 -> 0 | I68: ='Cost_structure (B2C)'!I36 -> 0 | ... T68: ='Cost_structure (B2C)'!T36 -> 0
A69: AJVC Cloud Credits | B69: 0 | C69: 0 | D69: 0 | E69: 0 | F69: 0 | G69: 0 | H69: 0 | I69: 0 | J69: 0 | K69: 0 | L69: 0 | M69: 0 | N69: 0 | O69: 0 | P69: 0 | Q69: 0 | R69: 0 | S69: 0 | T69: 0
A70: Credits Utilized | B70: 0 | C70: 0 | D70: 0 | E70: 0 | F70: 0 | G70: 0 | H70: 0 | I70: 0 | J70: 0 | K70: 0 | L70: 0 | M70: 0 | N70: 0 | O70: 0 | P70: 0 | Q70: 0 | R70: 0 | S70: 0 | T70: 0
A72: Investment
A73: AJVC Investment | C73: 15000000
A75: Cash Flow Statement
A76: Cash Begin
A77: Cash Flow from Operating Activities | C77: =C60 -> -100000 | D77: =D60 -> -300000 | E77: =E60 -> -404332 | F77: =F60 -> -656520 | G77: =G60 -> -736911 | H77: =H60 -> -710786 | I77: =I60 -> -838351 | J77: =J60 -> -794503 | ... T77: =T60 -> 16375726
A78: Cash Flow from Financing Activities | C78: =C73 -> 15000000
A79: Cash Flow from Investing Activities | C79: =-C68+C70 -> 0 | D79: =-D68+D70 -> 0 | E79: =-E68+E70 -> -259900 | F79: =-F68+F70 -> -289900 | G79: =-G68+G70 -> 0 | H79: =-H68+H70 -> 0 | I79: =-I68+I70 -> 0 | J79: =-J68+J70 -> 0 | ... T79: =-T68+T70 -> 0
A80: Cash End | C80: =SUM(C77:C79) -> 14900000 | D80: =SUM(D77:D79) -> -300000 | E80: =SUM(E77:E79) -> -664232 | F80: =SUM(F77:F79) -> -946420 | G80: =SUM(G77:G79) -> -736911 | H80: =SUM(H77:H79) -> -710786 | I80: =SUM(I77:I79) -> -838351 | J80: =SUM(J77:J79) -> -794503 | ... T80: =SUM(T77:T79) -> 16375726
A82: Worst Case in Case 0 Revenue for 18 Months
A84: Total Team Cost | B84: 9551308
A85: Total G&A | B85: 224700
A87: Funds Utilized | B87: =SUM(B84:B85)/15000000 -> 0.65173387

Sheet Explanations
A1: Sebi fee | B1: Applicable only after we become a SEBI-registered broker. SEBI charges a turnover-based fee of ₹10 per ₹1 crore of executed trading volume (i.e., 0.000001 × trading turnover).
A3: Trading volume | B3: Trading Volume refers to the total value of all buy and sell trades executed
A6: GlobalDatafeeds | B6: We plan to use GDF WebSocket API for real-time data. Below are the cost details. https://drive.google.com/file/d/1RKmgtAIpqGMickBIWK3pIdp6PzT4YkyJ/view?usp=sharing
A8: NSE DATA | B8: After becoming broker in Jan27 we will take all segments data from NSE directly https://www.nseindia.com/static/market-data/real-time-data-subscription
A10: High jump Dec26-Jan27 | B10: we will be apply for broker at the end of this year
A12: Youtube | B12: we are going to spend 50K/- month on two youtube channels as 1 ad on each
A14: Discord | B14: We believe that Discord delivers better outcomes than Telegram and YouTube, as it attracts higher-quality traders and enables deeper, more meaningful engagement.
A16: Cloud server | B16: Component, EC2 (2× t3.medium), RDS PostgreSQL, Load Balancer, Data Transfer, Storage + Backup, CloudWatch
A18: College visit | B18: Every month total 5 college visit
A20: Models | B20: we are going to use Claude opus 4.5, gemini 3 pro
A22: Laptop purchase | B22: mac m4 24gb, 48gb variants for doing multitask works like training models , android and web development simultaneously, contains 16 core gpu so help in design future simulation in equity and derivatives

Sheet Competitive landscape
A5: Competitive landscape | B5: https://drive.google.com/file/d/1GlDpYjiDuNZKbMoYQAe5ccXX4AjDWmYw/view?usp=sharing
